[
    { "env": "lab",   "os": "windows-2022", "arch": "x64", "tls": "schannel", "io": "iocp" },
    { "env": "lab",   "os": "windows-2022", "arch": "x64", "tls": "schannel", "io": "xdp" },
    { "env": "lab",   "os": "windows-2022", "arch": "x64", "tls": "schannel", "io": "wsk" },
    { "env": "lab",   "os": "ubuntu-20.04", "arch": "x64", "tls": "openssl",  "io": "epoll" },
    { "env": "lab",   "os": "ubuntu-22.04", "arch": "x64", "tls": "openssl3", "io": "epoll" },
    { "env": "lab",   "os": "ubuntu-22.04", "arch": "x64", "tls": "openssl3", "io": "xdp" }
]
